{"ENTITY_ID":19,"tables":[{"id":"24cdcae1-dc05-4751-bc26-dd99c89be857","position":{"x":1087,"y":-380},"data":{"table_name":"Credentials","fields":[{"fieldName":"id","fieldType":3,"isPK":true,"isNotNull":true,"isUnique":false,"defaultValue":"","args":"","isAutoIncrement":true},{"fieldName":"username","fieldType":10,"isPK":false,"isNotNull":true,"isUnique":true,"defaultValue":"","args":"32","isAutoIncrement":false},{"fieldName":"password","fieldType":10,"isPK":false,"isNotNull":true,"isUnique":false,"defaultValue":"","args":"128","isAutoIncrement":false}],"next_id":4,"checkName":[],"checkCondition":[]}},{"id":"fd6701f0-7e54-4f6c-992f-b3d81c22e90f","position":{"x":341,"y":-75},"data":{"table_name":"Artist","fields":[{"fieldName":"artistic_name","fieldType":10,"isPK":false,"isNotNull":true,"isUnique":true,"defaultValue":"","args":"128","isAutoIncrement":false}],"next_id":5,"checkName":[],"checkCondition":[]}},{"id":"d2ae78a0-e888-4e28-8225-ccbfb216238a","position":{"x":1115,"y":-94},"data":{"table_name":"Consumer","fields":[],"next_id":4,"checkName":[],"checkCondition":[]}},{"id":"079aabaf-9aef-41bd-9d26-4c00f066f770","position":{"x":728,"y":132},"data":{"table_name":"Song","fields":[{"fieldName":"ismn","fieldType":3,"isPK":true,"isNotNull":false,"isUnique":false,"defaultValue":"","args":[1,1],"isAutoIncrement":true},{"fieldName":"genre","fieldType":10,"isPK":false,"isNotNull":true,"isUnique":false,"defaultValue":"","args":"16","isAutoIncrement":false},{"fieldName":"title","fieldType":10,"isPK":false,"isNotNull":true,"isUnique":false,"defaultValue":"","args":"64","isAutoIncrement":false},{"fieldName":"release","fieldType":7,"isPK":false,"isNotNull":true,"isUnique":false,"defaultValue":"","args":"","isAutoIncrement":false},{"fieldName":"duration","fieldType":8,"isPK":false,"isNotNull":true,"isUnique":false,"defaultValue":"","args":"","isAutoIncrement":false}],"next_id":6,"checkName":[],"checkCondition":[]}},{"id":"ff3eec0e-41a2-4933-9401-35b575740536","position":{"x":312,"y":136},"data":{"table_name":"Label","fields":[{"fieldName":"id","fieldType":3,"isPK":true,"isNotNull":false,"isUnique":false,"defaultValue":"","args":[1,1],"isAutoIncrement":true},{"fieldName":"name","fieldType":10,"isPK":false,"isNotNull":true,"isUnique":true,"defaultValue":"","args":"128","isAutoIncrement":false},{"fieldName":"contact","fieldType":10,"isPK":false,"isNotNull":true,"isUnique":false,"defaultValue":"","args":"128","isAutoIncrement":false}],"next_id":3,"checkName":[],"checkCondition":[]}},{"id":"f8531f69-c91d-4192-9f37-2792a18f6257","position":{"x":59,"y":287},"data":{"table_name":"Album","fields":[{"fieldName":"id","fieldType":3,"isPK":true,"isNotNull":false,"isUnique":false,"defaultValue":"","args":[1,1],"isAutoIncrement":true},{"fieldName":"title","fieldType":10,"isPK":false,"isNotNull":true,"isUnique":false,"defaultValue":"","args":"64","isAutoIncrement":false},{"fieldName":"release","fieldType":7,"isPK":false,"isNotNull":true,"isUnique":false,"defaultValue":"","args":"","isAutoIncrement":false}],"next_id":4,"checkName":[],"checkCondition":[]}},{"id":"daa56c62-18b0-44bb-9714-bb98b054e89c","position":{"x":1293,"y":233},"data":{"table_name":"Playlist","fields":[{"fieldName":"id","fieldType":3,"isPK":true,"isNotNull":false,"isUnique":false,"defaultValue":"","args":[1,1],"isAutoIncrement":true},{"fieldName":"name","fieldType":10,"isPK":false,"isNotNull":true,"isUnique":false,"defaultValue":"","args":"64","isAutoIncrement":false},{"fieldName":"private","fieldType":0,"isPK":false,"isNotNull":true,"isUnique":false,"defaultValue":"","args":[1,1],"isAutoIncrement":false},{"fieldName":"top10","fieldType":0,"isPK":false,"isNotNull":true,"isUnique":false,"defaultValue":"False","args":[1,1],"isAutoIncrement":false}],"next_id":6,"checkName":[],"checkCondition":[]}},{"id":"451f2972-861d-4c3e-bd04-ad3a54dcb9d8","position":{"x":1503,"y":-114},"data":{"table_name":"Prepaid_Card","fields":[{"fieldName":"id","fieldType":10,"isPK":true,"isNotNull":false,"isUnique":false,"defaultValue":"","args":"16","isAutoIncrement":false},{"fieldName":"amount","fieldType":1,"isPK":false,"isNotNull":true,"isUnique":false,"defaultValue":"0","args":"","isAutoIncrement":false},{"fieldName":"expire","fieldType":7,"isPK":false,"isNotNull":true,"isUnique":false,"defaultValue":"","args":"","isAutoIncrement":false}],"next_id":4,"checkName":[],"checkCondition":[]}},{"id":"9f54a200-8f53-4d00-bb9b-7e3bfb912335","position":{"x":1117,"y":90},"data":{"table_name":"Comment","fields":[{"fieldName":"id","fieldType":3,"isPK":true,"isNotNull":false,"isUnique":false,"defaultValue":"","args":[1,1],"isAutoIncrement":true},{"fieldName":"content","fieldType":11,"isPK":false,"isNotNull":true,"isUnique":false,"defaultValue":"","args":["512"],"isAutoIncrement":false},{"fieldName":"comment_date","fieldType":7,"isPK":false,"isNotNull":true,"isUnique":false,"defaultValue":"","args":"","isAutoIncrement":false}],"next_id":3,"checkName":[],"checkCondition":[]}},{"id":"092e4988-948a-4d63-a162-a702620c297e","position":{"x":1492,"y":82},"data":{"table_name":"Subscription","fields":[{"fieldName":"id","fieldType":3,"isPK":true,"isNotNull":false,"isUnique":false,"defaultValue":"","args":[1,1],"isAutoIncrement":true},{"fieldName":"plan","fieldType":10,"isPK":false,"isNotNull":true,"isUnique":false,"defaultValue":"","args":"32","isAutoIncrement":false},{"fieldName":"start_date","fieldType":7,"isPK":false,"isNotNull":true,"isUnique":false,"defaultValue":"","args":"","isAutoIncrement":false},{"fieldName":"end_date","fieldType":7,"isPK":false,"isNotNull":true,"isUnique":false,"defaultValue":"","args":"","isAutoIncrement":false}],"next_id":4,"checkName":[],"checkCondition":[]}},{"id":"81cbb91f-9c21-4b12-9a88-b6368179f234","position":{"x":1368,"y":-243},"data":{"table_name":"Administrator","fields":[],"next_id":1,"checkName":[],"checkCondition":[]}},{"id":"e672849e-295b-43f8-90e1-751f77e8337d","position":{"x":804,"y":-245},"data":{"table_name":"Person","fields":[{"fieldName":"name","fieldType":10,"isPK":false,"isNotNull":true,"isUnique":false,"defaultValue":"","args":"256","isAutoIncrement":false},{"fieldName":"address","fieldType":10,"isPK":false,"isNotNull":true,"isUnique":false,"defaultValue":"","args":"256","isAutoIncrement":false},{"fieldName":"email","fieldType":10,"isPK":false,"isNotNull":true,"isUnique":true,"defaultValue":"","args":"128","isAutoIncrement":false},{"fieldName":"birthdate","fieldType":7,"isPK":false,"isNotNull":true,"isUnique":false,"defaultValue":"","args":"","isAutoIncrement":false}],"next_id":5,"checkName":[],"checkCondition":[]}},{"id":"bca8ed44-1a55-4521-9c4b-1f968995633b","position":{"x":748,"y":-53},"data":{"table_name":"Consumer_Song","fields":[{"fieldName":"views","fieldType":1,"isPK":false,"isNotNull":true,"isUnique":false,"defaultValue":"0","args":"","isAutoIncrement":false},{"fieldName":"listen_date","fieldType":7,"isPK":false,"isNotNull":true,"isUnique":false,"defaultValue":"","args":"","isAutoIncrement":false}],"next_id":4,"checkName":[],"checkCondition":[]}},{"id":"694e3409-1a4e-4df9-92d1-1104437694f9","position":{"x":1691,"y":0},"data":{"table_name":"Transaction","fields":[{"fieldName":"id","fieldType":3,"isPK":true,"isNotNull":false,"isUnique":false,"defaultValue":"","args":"","isAutoIncrement":true},{"fieldName":"transaction_date","fieldType":0,"isPK":false,"isNotNull":true,"isUnique":false,"defaultValue":"","args":[1,1],"isAutoIncrement":false}],"next_id":5,"checkName":[],"checkCondition":[]}}],"links":[{"source":"fd6701f0-7e54-4f6c-992f-b3d81c22e90f","target":"e672849e-295b-43f8-90e1-751f77e8337d","order":"parenting","sourceCard":"0:1","targetCard":"0:1","label":"complete","hierType":"complete","sourceisweak":false,"targetisweak":false},{"source":"d2ae78a0-e888-4e28-8225-ccbfb216238a","target":"e672849e-295b-43f8-90e1-751f77e8337d","order":"parenting","sourceCard":"0:1","targetCard":"0:1","label":"complete","hierType":"complete","sourceisweak":false,"targetisweak":false},{"source":"9f54a200-8f53-4d00-bb9b-7e3bfb912335","target":"079aabaf-9aef-41bd-9d26-4c00f066f770","order":"normal","sourceCard":"0:n","targetCard":"1:1","label":"comment","hierType":null,"sourceisweak":false,"targetisweak":false},{"source":"9f54a200-8f53-4d00-bb9b-7e3bfb912335","target":"9f54a200-8f53-4d00-bb9b-7e3bfb912335","order":"normal","sourceCard":"0:n","targetCard":"1:1","label":"comment chain","hierType":null,"sourceisweak":false,"targetisweak":false},{"source":"079aabaf-9aef-41bd-9d26-4c00f066f770","target":"daa56c62-18b0-44bb-9714-bb98b054e89c","order":"normal","sourceCard":"0:n","targetCard":"0:n","label":"has","hierType":null,"sourceisweak":false,"targetisweak":false},{"source":"d2ae78a0-e888-4e28-8225-ccbfb216238a","target":"daa56c62-18b0-44bb-9714-bb98b054e89c","order":"normal","sourceCard":"1:n","targetCard":"0:n","label":"create","hierType":null,"sourceisweak":false,"targetisweak":false},{"source":"079aabaf-9aef-41bd-9d26-4c00f066f770","target":"fd6701f0-7e54-4f6c-992f-b3d81c22e90f","order":"normal","sourceCard":"0:n","targetCard":"1:n","label":"create","hierType":null,"sourceisweak":false,"targetisweak":false},{"source":"f8531f69-c91d-4192-9f37-2792a18f6257","target":"fd6701f0-7e54-4f6c-992f-b3d81c22e90f","order":"normal","sourceCard":"0:n","targetCard":"1:n","label":"create","hierType":null,"sourceisweak":false,"targetisweak":false},{"source":"e672849e-295b-43f8-90e1-751f77e8337d","target":"24cdcae1-dc05-4751-bc26-dd99c89be857","order":"parenting","sourceCard":"0:1","targetCard":"0:1","label":"complete","hierType":"complete","sourceisweak":false,"targetisweak":false},{"source":"81cbb91f-9c21-4b12-9a88-b6368179f234","target":"24cdcae1-dc05-4751-bc26-dd99c89be857","order":"parenting","sourceCard":"0:1","targetCard":"0:1","label":"complete","hierType":"complete","sourceisweak":false,"targetisweak":false},{"source":"079aabaf-9aef-41bd-9d26-4c00f066f770","target":"bca8ed44-1a55-4521-9c4b-1f968995633b","order":"normal","sourceCard":"1:1","targetCard":"0:n","label":"relation","hierType":null,"sourceisweak":false,"targetisweak":true},{"source":"bca8ed44-1a55-4521-9c4b-1f968995633b","target":"d2ae78a0-e888-4e28-8225-ccbfb216238a","order":"normal","sourceCard":"0:n","targetCard":"1:1","label":"relation","hierType":null,"sourceisweak":true,"targetisweak":false},{"source":"f8531f69-c91d-4192-9f37-2792a18f6257","target":"079aabaf-9aef-41bd-9d26-4c00f066f770","order":"normal","sourceCard":"0:n","targetCard":"1:n","label":"has","hierType":null,"sourceisweak":false,"targetisweak":false},{"source":"ff3eec0e-41a2-4933-9401-35b575740536","target":"fd6701f0-7e54-4f6c-992f-b3d81c22e90f","order":"normal","sourceCard":"1:1","targetCard":"0:n","label":"has","hierType":null,"sourceisweak":false,"targetisweak":false},{"source":"ff3eec0e-41a2-4933-9401-35b575740536","target":"079aabaf-9aef-41bd-9d26-4c00f066f770","order":"normal","sourceCard":"1:1","targetCard":"0:n","label":"publish","hierType":null,"sourceisweak":false,"targetisweak":false},{"source":"d2ae78a0-e888-4e28-8225-ccbfb216238a","target":"9f54a200-8f53-4d00-bb9b-7e3bfb912335","order":"normal","sourceCard":"1:1","targetCard":"0:n","label":"comment","hierType":null,"sourceisweak":false,"targetisweak":true},{"source":"f8531f69-c91d-4192-9f37-2792a18f6257","target":"ff3eec0e-41a2-4933-9401-35b575740536","order":"normal","sourceCard":"0:n","targetCard":"1:1","label":"has","hierType":null,"sourceisweak":false,"targetisweak":false},{"source":"81cbb91f-9c21-4b12-9a88-b6368179f234","target":"451f2972-861d-4c3e-bd04-ad3a54dcb9d8","order":"normal","sourceCard":"1:1","targetCard":"0:n","label":"create","hierType":null,"sourceisweak":false,"targetisweak":false},{"source":"d2ae78a0-e888-4e28-8225-ccbfb216238a","target":"092e4988-948a-4d63-a162-a702620c297e","order":"normal","sourceCard":"0:n","targetCard":"0:n","label":"subscribe","hierType":null,"sourceisweak":false,"targetisweak":false},{"source":"451f2972-861d-4c3e-bd04-ad3a54dcb9d8","target":"694e3409-1a4e-4df9-92d1-1104437694f9","order":"normal","sourceCard":"1:n","targetCard":"0:n","label":"used","hierType":null,"sourceisweak":false,"targetisweak":false},{"source":"092e4988-948a-4d63-a162-a702620c297e","target":"694e3409-1a4e-4df9-92d1-1104437694f9","order":"normal","sourceCard":"1:1","targetCard":"1:1","label":"used","hierType":null,"sourceisweak":false,"targetisweak":false},{"source":"d2ae78a0-e888-4e28-8225-ccbfb216238a","target":"451f2972-861d-4c3e-bd04-ad3a54dcb9d8","order":"normal","sourceCard":"0:1","targetCard":"0:n","label":"","hierType":null,"sourceisweak":false,"targetisweak":false}],"normalization":1,"database":0}